setup.py
bin/cp_to_anki_colorizer
cp_to_anki_colorizer/__init__.py
cp_to_anki_colorizer/colorize_lines.py
cp_to_anki_colorizer/colorizer.py
cp_to_anki_colorizer.egg-info/PKG-INFO
cp_to_anki_colorizer.egg-info/SOURCES.txt
cp_to_anki_colorizer.egg-info/dependency_links.txt
cp_to_anki_colorizer.egg-info/requires.txt
cp_to_anki_colorizer.egg-info/top_level.txt