Metadata-Version: 1.0
Name: cp-to-anki-colorizer
Version: 0.7
Summary: Colorizes tones in Hanzi and Pinyin from ChinesePod vocab list export in a format that Anki can import
Home-page: UNKNOWN
Author: Alex Keyes
Author-email: alexander.r.keyes@gmail.com
License: UNKNOWN
Platform: UNKNOWN
